[
  {
    "Id": 1,
    "title": "Modern Luxury Home with Garden",
    "price": 850000,
    "type": "house",
    "bedrooms": 4,
    "bathrooms": 3,
    "sqft": 2800,
    "address": "123 Maple Street",
    "city": "San Francisco",
    "state": "CA",
    "zipCode": "94102",
    "description": "Beautiful modern home featuring an open-concept design with high ceilings, gourmet kitchen with granite countertops, and a spacious master suite. The property includes a landscaped garden, two-car garage, and is located in a quiet residential neighborhood close to schools and parks.",
    "images": [
      "https://images.unsplash.com/photo-1600596542815-ffad4c1539a9?ixlib=rb-4.0.3&ixid=M3wxMjA3fDB8MHxwaG90by1wYWdlfHx8fGVufDB8fHx8fA%3D%3D&auto=format&fit=crop&w=2075&q=80",
      "https://images.unsplash.com/photo-1600047509807-ba8f99d2cdde?ixlib=rb-4.0.3&ixid=M3wxMjA3fDB8MHxwaG90by1wYWdlfHx8fGVufDB8fHx8fA%3D%3D&auto=format&fit=crop&w=2070&q=80",
      "https://images.unsplash.com/photo-1600566753086-00f18fb6b3ea?ixlib=rb-4.0.3&ixid=M3wxMjA3fDB8MHxwaG90by1wYWdlfHx8fGVufDB8fHx8fA%3D%3D&auto=format&fit=crop&w=2070&q=80",
      "https://images.unsplash.com/photo-1560448204-e02f11c3d0e2?ixlib=rb-4.0.3&ixid=M3wxMjA3fDB8MHxwaG90by1wYWdlfHx8fGVufDB8fHx8fA%3D%3D&auto=format&fit=crop&w=2070&q=80"
    ],
    "amenities": [
      "Central Air Conditioning",
      "Hardwood Floors",
      "Granite Countertops",
      "Walk-in Closets",
      "Private Garden",
      "Two-Car Garage",
      "Fireplace",
      "Updated Kitchen"
    ],
    "yearBuilt": 2018,
    "parking": "2-car garage",
    "lat": 37.7749,
    "lng": -122.4194,
    "listedDate": "2024-01-15T00:00:00.000Z",
    "status": "for-sale"
  },
  {
    "Id": 2,
    "title": "Downtown Luxury Apartment",
    "price": 3200,
    "type": "apartment",
    "bedrooms": 2,
    "bathrooms": 2,
    "sqft": 1200,
    "address": "456 Market Street",
    "city": "San Francisco",
    "state": "CA",
    "zipCode": "94105",
    "description": "Stunning downtown apartment with floor-to-ceiling windows offering panoramic city views. Features include a modern kitchen with stainless steel appliances, in-unit washer/dryer, and access to building amenities including rooftop deck, fitness center, and concierge service.",
    "images": [
      "https://images.unsplash.com/photo-1522708323590-d24dbb6b0267?ixlib=rb-4.0.3&ixid=M3wxMjA3fDB8MHxwaG90by1wYWdlfHx8fGVufDB8fHx8fA%3D%3D&auto=format&fit=crop&w=2070&q=80",
      "https://images.unsplash.com/photo-1502672260266-1c1ef2d93688?ixlib=rb-4.0.3&ixid=M3wxMjA3fDB8MHxwaG90by1wYWdlfHx8fGVufDB8fHx8fA%3D%3D&auto=format&fit=crop&w=2080&q=80",
      "https://images.unsplash.com/photo-1493809842364-78817add7ffb?ixlib=rb-4.0.3&ixid=M3wxMjA3fDB8MHxwaG90by1wYWdlfHx8fGVufDB8fHx8fA%3D%3D&auto=format&fit=crop&w=2070&q=80"
    ],
    "amenities": [
      "Floor-to-Ceiling Windows",
      "City Views",
      "In-Unit Washer/Dryer",
      "Stainless Steel Appliances",
      "Rooftop Deck",
      "Fitness Center",
      "Concierge Service",
      "Parking Space"
    ],
    "yearBuilt": 2020,
    "parking": "1 space included",
    "lat": 37.7849,
    "lng": -122.4094,
    "listedDate": "2024-01-10T00:00:00.000Z",
    "status": "for-rent"
  },
  {
    "Id": 3,
    "title": "Charming Victorian Townhouse",
    "price": 1200000,
    "type": "townhouse",
    "bedrooms": 3,
    "bathrooms": 2,
    "sqft": 1800,
    "address": "789 Valencia Street",
    "city": "San Francisco",
    "state": "CA",
    "zipCode": "94110",
    "description": "Beautifully restored Victorian townhouse in the heart of the Mission District. This historic home combines original architectural details with modern amenities. Features include restored hardwood floors, original moldings, updated kitchen and bathrooms, and a private patio perfect for entertaining.",
    "images": [
      "https://images.unsplash.com/photo-1570129477492-45c003edd2be?ixlib=rb-4.0.3&ixid=M3wxMjA3fDB8MHxwaG90by1wYWdlfHx8fGVufDB8fHx8fA%3D%3D&auto=format&fit=crop&w=2070&q=80",
      "https://images.unsplash.com/photo-1564013799919-ab600027ffc6?ixlib=rb-4.0.3&ixid=M3wxMjA3fDB8MHxwaG90by1wYWdlfHx8fGVufDB8fHx8fA%3D%3D&auto=format&fit=crop&w=2070&q=80",
      "https://images.unsplash.com/photo-1505843513577-22bb7d21e455?ixlib=rb-4.0.3&ixid=M3wxMjA3fDB8MHxwaG90by1wYWdlfHx8fGVufDB8fHx8fA%3D%3D&auto=format&fit=crop&w=2064&q=80"
    ],
    "amenities": [
      "Original Victorian Details",
      "Restored Hardwood Floors",
      "Original Moldings",
      "Updated Kitchen",
      "Private Patio",
      "High Ceilings",
      "Historic Character",
      "Central Location"
    ],
    "yearBuilt": 1905,
    "parking": "Street parking",
    "lat": 37.7599,
    "lng": -122.4194,
    "listedDate": "2024-01-20T00:00:00.000Z",
    "status": "for-sale"
  },
  {
    "Id": 4,
    "title": "Spacious Family Home with Pool",
    "price": 1500000,
    "type": "house",
    "bedrooms": 5,
    "bathrooms": 4,
    "sqft": 3500,
    "address": "321 Oak Avenue",
    "city": "Palo Alto",
    "state": "CA",
    "zipCode": "94301",
    "description": "Exceptional family home in prestigious neighborhood featuring an open floor plan, gourmet kitchen with island, formal dining room, and spacious family room. The backyard oasis includes a swimming pool, spa, and mature landscaping. Perfect for entertaining and family living.",
    "images": [
      "https://images.unsplash.com/photo-1613490493576-7fde63acd811?ixlib=rb-4.0.3&ixid=M3wxMjA3fDB8MHxwaG90by1wYWdlfHx8fGVufDB8fHx8fA%3D%3D&auto=format&fit=crop&w=2071&q=80",
      "https://images.unsplash.com/photo-1600607687939-ce8a6c25118c?ixlib=rb-4.0.3&ixid=M3wxMjA3fDB8MHxwaG90by1wYWdlfHx8fGVufDB8fHx8fA%3D%3D&auto=format&fit=crop&w=2053&q=80",
      "https://images.unsplash.com/photo-1600566753190-17f0baa2a6c3?ixlib=rb-4.0.3&ixid=M3wxMjA3fDB8MHxwaG90by1wYWdlfHx8fGVufDB8fHx8fA%3D%3D&auto=format&fit=crop&w=2070&q=80"
    ],
    "amenities": [
      "Swimming Pool",
      "Spa/Hot Tub",
      "Gourmet Kitchen",
      "Kitchen Island",
      "Formal Dining Room",
      "Family Room",
      "Mature Landscaping",
      "Three-Car Garage"
    ],
    "yearBuilt": 2010,
    "parking": "3-car garage",
    "lat": 37.4419,
    "lng": -122.1430,
    "listedDate": "2024-01-05T00:00:00.000Z",
    "status": "for-sale"
  },
  {
    "Id": 5,
    "title": "Contemporary Loft in SOMA",
    "price": 4500,
    "type": "loft",
    "bedrooms": 1,
    "bathrooms": 1,
    "sqft": 900,
    "address": "654 Bryant Street",
    "city": "San Francisco",
    "state": "CA",
    "zipCode": "94107",
    "description": "Industrial-style loft with exposed brick walls, concrete floors, and soaring ceilings. This open-concept space features a modern kitchen with stainless steel appliances, oversized windows flooding the space with natural light, and access to a shared rooftop terrace with stunning city views.",
    "images": [
      "https://images.unsplash.com/photo-1484154218962-a197022b5858?ixlib=rb-4.0.3&ixid=M3wxMjA3fDB8MHxwaG90by1wYWdlfHx8fGVufDB8fHx8fA%3D%3D&auto=format&fit=crop&w=2074&q=80",
      "https://images.unsplash.com/photo-1507089947368-19c1da9775ae?ixlib=rb-4.0.3&ixid=M3wxMjA3fDB8MHxwaG90by1wYWdlfHx8fGVufDB8fHx8fA%3D%3D&auto=format&fit=crop&w=2076&q=80",
      "https://images.unsplash.com/photo-1449844908441-8829872d2607?ixlib=rb-4.0.3&ixid=M3wxMjA3fDB8MHxwaG90by1wYWdlfHx8fGVufDB8fHx8fA%3D%3D&auto=format&fit=crop&w=2070&q=80"
    ],
    "amenities": [
      "Exposed Brick Walls",
      "Concrete Floors",
      "High Ceilings",
      "Open Concept",
      "Oversized Windows",
      "Rooftop Terrace",
      "Industrial Style",
      "Natural Light"
    ],
    "yearBuilt": 2015,
    "parking": "Street parking",
    "lat": 37.7749,
    "lng": -122.3994,
    "listedDate": "2024-01-12T00:00:00.000Z",
    "status": "for-rent"
  },
  {
    "Id": 6,
    "title": "Elegant Condo with Bay Views",
    "price": 975000,
    "type": "condo",
    "bedrooms": 2,
    "bathrooms": 2,
    "sqft": 1400,
    "address": "987 Marina Boulevard",
    "city": "San Francisco",
    "state": "CA",
    "zipCode": "94123",
    "description": "Sophisticated condominium offering breathtaking views of the San Francisco Bay and Golden Gate Bridge. This elegant unit features hardwood floors throughout, a chef's kitchen with premium appliances, master suite with walk-in closet, and in-unit laundry. Building amenities include doorman and fitness center.",
    "images": [
      "https://images.unsplash.com/photo-1502672260266-1c1ef2d93688?ixlib=rb-4.0.3&ixid=M3wxMjA3fDB8MHxwaG90by1wYWdlfHx8fGVufDB8fHx8fA%3D%3D&auto=format&fit=crop&w=2080&q=80",
      "https://images.unsplash.com/photo-1560184897-ae75f418493e?ixlib=rb-4.0.3&ixid=M3wxMjA3fDB8MHxwaG90by1wYWdlfHx8fGVufDB8fHx8fA%3D%3D&auto=format&fit=crop&w=2070&q=80",
      "https://images.unsplash.com/photo-1600210492486-724fe5c67fb0?ixlib=rb-4.0.3&ixid=M3wxMjA3fDB8MHxwaG90by1wYWdlfHx8fGVufDB8fHx8fA%3D%3D&auto=format&fit=crop&w=2074&q=80"
    ],
    "amenities": [
      "Bay Views",
      "Golden Gate Bridge Views",
      "Hardwood Floors",
      "Chef's Kitchen",
      "Premium Appliances",
      "Walk-in Closet",
      "Doorman",
      "Fitness Center"
    ],
    "yearBuilt": 2016,
    "parking": "1 space included",
    "lat": 37.8019,
    "lng": -122.4362,
    "listedDate": "2024-01-18T00:00:00.000Z",
    "status": "for-sale"
  },
  {
    "Id": 7,
    "title": "Cozy Cottage in Noe Valley",
    "price": 2800,
    "type": "house",
    "bedrooms": 2,
    "bathrooms": 1,
    "sqft": 1000,
    "address": "234 Dolores Street",
    "city": "San Francisco",
    "state": "CA",
    "zipCode": "94114",
    "description": "Charming cottage in desirable Noe Valley neighborhood. This adorable home features original hardwood floors, vintage tile bathroom, cozy living room with fireplace, and a sunny kitchen. The property includes a small garden and is walking distance to excellent restaurants and shops.",
    "images": [
      "https://images.unsplash.com/photo-1449844908441-8829872d2607?ixlib=rb-4.0.3&ixid=M3wxMjA3fDB8MHxwaG90by1wYWdlfHx8fGVufDB8fHx8fA%3D%3D&auto=format&fit=crop&w=2070&q=80",
      "https://images.unsplash.com/photo-1505843513577-22bb7d21e455?ixlib=rb-4.0.3&ixid=M3wxMjA3fDB8MHxwaG90by1wYWdlfHx8fGVufDB8fHx8fA%3D%3D&auto=format&fit=crop&w=2064&q=80",
      "https://images.unsplash.com/photo-1560184897-ae75f418493e?ixlib=rb-4.0.3&ixid=M3wxMjA3fDB8MHxwaG90by1wYWdlfHx8fGVufDB8fHx8fA%3D%3D&auto=format&fit=crop&w=2070&q=80"
    ],
    "amenities": [
      "Original Hardwood Floors",
      "Vintage Tile Bathroom",
      "Fireplace",
      "Sunny Kitchen",
      "Small Garden",
      "Charming Character",
      "Walkable Neighborhood",
      "Cozy Layout"
    ],
    "yearBuilt": 1925,
    "parking": "Street parking",
    "lat": 37.7510,
    "lng": -122.4267,
    "listedDate": "2024-01-08T00:00:00.000Z",
    "status": "for-rent"
  },
  {
    "Id": 8,
    "title": "Modern Penthouse with Terrace",
    "price": 2200000,
    "type": "condo",
    "bedrooms": 3,
    "bathrooms": 3,
    "sqft": 2200,
    "address": "555 Mission Street",
    "city": "San Francisco",
    "state": "CA",
    "zipCode": "94105",
    "description": "Spectacular penthouse offering 360-degree views of the city, bay, and mountains. This luxurious residence features floor-to-ceiling windows, a gourmet kitchen with top-of-the-line appliances, three en-suite bedrooms, and a private terrace perfect for entertaining. Premium building amenities included.",
    "images": [
      "https://images.unsplash.com/photo-1613490493576-7fde63acd811?ixlib=rb-4.0.3&ixid=M3wxMjA3fDB8MHxwaG90by1wYWdlfHx8fGVufDB8fHx8fA%3D%3D&auto=format&fit=crop&w=2071&q=80",
      "https://images.unsplash.com/photo-1493809842364-78817add7ffb?ixlib=rb-4.0.3&ixid=M3wxMjA3fDB8MHxwaG90by1wYWdlfHx8fGVufDB8fHx8fA%3D%3D&auto=format&fit=crop&w=2070&q=80",
      "https://images.unsplash.com/photo-1522708323590-d24dbb6b0267?ixlib=rb-4.0.3&ixid=M3wxMjA3fDB8MHxwaG90by1wYWdlfHx8fGVufDB8fHx8fA%3D%3D&auto=format&fit=crop&w=2070&q=80"
    ],
    "amenities": [
      "360-Degree Views",
      "Private Terrace",
      "Floor-to-Ceiling Windows",
      "Gourmet Kitchen",
      "Top-of-the-Line Appliances",
      "En-Suite Bathrooms",
      "Luxury Building",
      "Concierge Service"
    ],
    "yearBuilt": 2021,
    "parking": "2 spaces included",
    "lat": 37.7888,
    "lng": -122.3967,
    "listedDate": "2024-01-22T00:00:00.000Z",
    "status": "for-sale"
  },
  {
    "Id": 9,
    "title": "Renovated Apartment in Castro",
    "price": 3800,
    "type": "apartment",
    "bedrooms": 2,
    "bathrooms": 1,
    "sqft": 1100,
    "address": "876 Castro Street",
    "city": "San Francisco",
    "state": "CA",
    "zipCode": "94114",
    "description": "Fully renovated apartment in the vibrant Castro district. This bright and airy unit features new hardwood floors, updated kitchen with quartz countertops, renovated bathroom, and plenty of natural light. Located steps from Muni, restaurants, and nightlife.",
    "images": [
      "https://images.unsplash.com/photo-1560184897-ae75f418493e?ixlib=rb-4.0.3&ixid=M3wxMjA3fDB8MHxwaG90by1wYWdlfHx8fGVufDB8fHx8fA%3D%3D&auto=format&fit=crop&w=2070&q=80",
      "https://images.unsplash.com/photo-1484154218962-a197022b5858?ixlib=rb-4.0.3&ixid=M3wxMjA3fDB8MHxwaG90by1wYWdlfHx8fGVufDB8fHx8fA%3D%3D&auto=format&fit=crop&w=2074&q=80",
      "https://images.unsplash.com/photo-1507089947368-19c1da9775ae?ixlib=rb-4.0.3&ixid=M3wxMjA3fDB8MHxwaG90by1wYWdlfHx8fGVufDB8fHx8fA%3D%3D&auto=format&fit=crop&w=2076&q=80"
    ],
    "amenities": [
      "Fully Renovated",
      "New Hardwood Floors",
      "Quartz Countertops",
      "Updated Kitchen",
      "Renovated Bathroom",
      "Natural Light",
      "Transit Accessible",
      "Vibrant Neighborhood"
    ],
    "yearBuilt": 1940,
    "parking": "Street parking",
    "lat": 37.7609,
    "lng": -122.4350,
    "listedDate": "2024-01-14T00:00:00.000Z",
    "status": "for-rent"
  }
]